CHANGES.rst
LICENSE
MANIFEST.in
README.rst
setup.py
jctconv/__init__.py
jctconv/compat.py
jctconv/conv_table.py
jctconv/jctconv.py
jctconv.egg-info/.DS_Store
jctconv.egg-info/PKG-INFO
jctconv.egg-info/SOURCES.txt
jctconv.egg-info/dependency_links.txt
jctconv.egg-info/top_level.txt