Metadata-Version: 1.1
Name: jctconv
Version: 0.1.1.1
Summary: Pure-Python Japanese character interconverter for Hiragana, Katakana, Hankaku and Zenkaku
Home-page: https://github.com/ikegami-yukino/jctconv
Author: Yukino Ikegami
Author-email: yukino0131@me.com
License: MIT License
Keywords: japanese converter,half-width kana,Hiragana,Katakana,Hankaku,Zenkaku
Platform: POSIX
Platform: Windows
Platform: Unix
Platform: MacOS
Classifier: Development Status :: 4 - Beta
Classifier: Intended Audience :: Developers
Classifier: Intended Audience :: Information Technology
Classifier: License :: OSI Approved :: MIT License
Classifier: Natural Language :: Japanese
Classifier: Operating System :: MacOS
Classifier: Operating System :: Microsoft
Classifier: Operating System :: POSIX
Classifier: Programming Language :: Python :: 2.6
Classifier: Programming Language :: Python :: 2.7
Classifier: Programming Language :: Python :: 3.3
Classifier: Programming Language :: Python :: 3.4
Classifier: Programming Language :: Python :: 3.5
Classifier: Topic :: Text Processing
